pycpqcc/__init__.py
pycpqcc/parse.py
pycpqcc/data/ca_coords.csv
pycpqcc/data/gis/CA_State.zip
pycpqcc/data/icd/$dxref 2015.csv
pycpqcc/data/icd/$prref 2015.csv
pycpqcc/data/icd/ccs_dx_icd10cm_2017.csv
pycpqcc/data/icd/ccs_pr_icd10pcs_2017.csv
pycpqcc-0.15.dist-info/LICENSE
pycpqcc-0.15.dist-info/METADATA
pycpqcc-0.15.dist-info/WHEEL
pycpqcc-0.15.dist-info/top_level.txt
pycpqcc-0.15.dist-info/RECORD
