Metadata-Version: 2.1
Name: pycpqcc
Version: 0.15
Summary: Python package for CPQCC
Home-page: UNKNOWN
Author: Daniel Helkey
Author-email: dhelkey@stanford.edu
License: MIT
Platform: UNKNOWN
